{"frames":[{"filename":"MineDanger_01","frame":{"x":0,"y":0,"w":63,"h":42},"rotated":false,"trimmed":false,"spriteSourceSize":{"x":0,"y":0,"w":63,"h":42},"sourceSize":{"w":63,"h":42}},{"filename":"MineDanger_02","frame":{"x":0,"y":43,"w":63,"h":42},"rotated":false,"trimmed":false,"spriteSourceSize":{"x":0,"y":0,"w":63,"h":42},"sourceSize":{"w":63,"h":42}},{"filename":"MineIdle_01","frame":{"x":64,"y":0,"w":63,"h":42},"rotated":false,"trimmed":false,"spriteSourceSize":{"x":0,"y":0,"w":63,"h":42},"sourceSize":{"w":63,"h":42}},{"filename":"MineIdle_02","frame":{"x":64,"y":43,"w":63,"h":42},"rotated":false,"trimmed":false,"spriteSourceSize":{"x":0,"y":0,"w":63,"h":42},"sourceSize":{"w":63,"h":42}}],"meta":{"app":"http://www.leshylabs.com/apps/sstool/","version":"Leshy SpriteSheet Tool v0.8.1","size":{"w":127,"h":85},"scale":1}}